README.txt
setup.py
socketless/__init__.py
socketless/channel.c
socketless/channelserver.py
socketless/messenger.c
socketless/ropebuffer.c
socketless/serialize.c
socketless/service.c
socketless.egg-info/PKG-INFO
socketless.egg-info/SOURCES.txt
socketless.egg-info/dependency_links.txt
socketless.egg-info/requires.txt
socketless.egg-info/top_level.txt
socketless.egg-info/zip-safe